MANIFEST.in
README.md
README.rst
requirements.txt
setup.cfg
setup.py
fbtimer/__init__.py
fbtimer/cli.py
fbtimer/util.py
fbtimer.egg-info/PKG-INFO
fbtimer.egg-info/SOURCES.txt
fbtimer.egg-info/dependency_links.txt
fbtimer.egg-info/entry_points.txt
fbtimer.egg-info/requires.txt
fbtimer.egg-info/top_level.txt
fbtimer/model/__init__.py
fbtimer/model/client.py
fbtimer/model/project.py
fbtimer/model/timer.py
fbtimer/model/user.py
fbtimer/service/__init__.py
fbtimer/service/auth.py
fbtimer/service/client.py
fbtimer/service/config.py
fbtimer/service/project.py
fbtimer/service/time_entry.py
fbtimer/service/timer.py
fbtimer/service/user.py
tests/__init__.py
tests/component/__init__.py
tests/component/test_timer_details.py
tests/component/test_timers.py
tests/unit/__init__.py
tests/unit/test_config.py