Metadata-Version: 1.1
Name: fbtimer
Version: 0.1.0
Summary: Track time in FreshBooks via the command line
Home-page: https://github.com/amcintosh/FreshBooks-Timer
Author: Andrew McIntosh
Author-email: andrew@amcintosh.net
License: MIT
Download-URL: https://github.com/amcintosh/FreshBooks-Timer/archive/0.1.0.tar.gz
Keywords: FreshBooks,Time Tracking
Platform: UNKNOWN
